census_parquet/__init__.py
census_parquet/cli.py
census_parquet/download_blocks.sh
census_parquet/download_boundaries.sh
census_parquet/download_population_stats.sh
census_parquet/process_blocks.py
census_parquet/process_boundaries.py
census_parquet-0.0.9.dist-info/LICENSE.txt
census_parquet-0.0.9.dist-info/METADATA
census_parquet-0.0.9.dist-info/WHEEL
census_parquet-0.0.9.dist-info/entry_points.txt
census_parquet-0.0.9.dist-info/top_level.txt
census_parquet-0.0.9.dist-info/RECORD
