Metadata-Version: 2.1
Name: census-parquet
Version: 0.0.9
Summary: Tools for generating Parquet files from US Census 2020
Home-page: https://github.com/makepath/census-parquet
Author: makepath
License: MIT
Platform: UNKNOWN
Requires-Dist: click
Requires-Dist: dask-geopandas
Requires-Dist: openpyxl
Requires-Dist: pyarrow
